Metadata-Version: 2.1
Name: yamtof
Version: 0.1
Summary: Yamtof provides a simple and convenient interface for writing multi-phase optimal control problems.
Home-page: https://github.com/janismac/yamtof
Author: Janis Maczijewski
Author-email: Janis.Maczijewski@rwth-aachen.de
License: apache-2.0
Download-URL: https://github.com/janismac/yamtof/archive/v0.1.tar.gz
Platform: UNKNOWN
Classifier: Development Status :: 3 - Alpha
Classifier: License :: OSI Approved :: Apache Software License
Classifier: Programming Language :: Python :: 3
Classifier: Programming Language :: Python :: 3.7
